README.md
setup.py
CuteR/CuteR.py
CuteR/__init__.py
CuteR.egg-info/PKG-INFO
CuteR.egg-info/SOURCES.txt
CuteR.egg-info/dependency_links.txt
CuteR.egg-info/entry_points.txt
CuteR.egg-info/requires.txt
CuteR.egg-info/top_level.txt