Metadata-Version: 1.0
Name: CuteR
Version: 1.4.1
Summary: Custom QR Code with picture
Home-page: https://github.com/chinuno-usami/CuteR
Author: Chinuno Usami
Author-email: usami@chinuno.com
License: GPLv3
Platform: UNKNOWN
